setup.py
easy_drf/__init__.py
easy_drf/version.py
easy_drf.egg-info/PKG-INFO
easy_drf.egg-info/SOURCES.txt
easy_drf.egg-info/dependency_links.txt
easy_drf.egg-info/requires.txt
easy_drf.egg-info/top_level.txt
easy_drf/decorators/__init__.py
easy_drf/decorators/etag.py
easy_drf/views/__init__.py
easy_drf/views/model_flat_etag_viewset.py
tests/__init__.py
tests/test_version.py