Metadata-Version: 1.1
Name: easy-drf
Version: 0.1.1
Summary: Django Rest Framework Become Easy
Home-page: https://github.com/talp101/easy-drf.git
Author: Tal Peretz
Author-email: 13@1500.co.il
License: MIT
Keywords: django djangorestframework
Platform: UNKNOWN
Classifier: Development Status :: 4 - Beta
Classifier: Intended Audience :: Developers
Classifier: License :: OSI Approved :: MIT License
Classifier: Natural Language :: English
Classifier: Operating System :: Unix
Classifier: Programming Language :: Python :: 2.7
Classifier: Programming Language :: Python :: 3.4
Classifier: Operating System :: OS Independent
